biobb_wf_mutations/__init__.py
biobb_wf_mutations/notebooks/mutations.ipynb
biobb_wf_mutations/pycompss/__init__.py
biobb_wf_mutations/pycompss/mutations.py
biobb_wf_mutations/python/__init__.py
biobb_wf_mutations/python/mutations.py
biobb_wf_mutations-0.0.6.dist-info/METADATA
biobb_wf_mutations-0.0.6.dist-info/RECORD
biobb_wf_mutations-0.0.6.dist-info/WHEEL
biobb_wf_mutations-0.0.6.dist-info/top_level.txt
