Metadata-Version: 2.1
Name: biobb-wf-mutations
Version: 0.0.6
Summary: Lysozyme + Mutations workflow built using BioBB Based on the official Gromacs tutorial: http://www.mdtutorials.com/gmx/lysozyme/01_pdb2gmx.html
Home-page: https://github.com/bioexcel/biobb_md
Author: Biobb developers
Author-email: pau.andrio@bsc.es
License: UNKNOWN
Project-URL: Documentation, http://biobb_wf_mutations.readthedocs.io/en/latest/
Project-URL: Bioexcel, https://bioexcel.eu/
Keywords: Bioinformatics Workflows BioExcel Compatibility
Platform: UNKNOWN
Classifier: Development Status :: 3 - Alpha
Classifier: Programming Language :: Python :: 3
Classifier: License :: OSI Approved :: Apache Software License
Classifier: Operating System :: MacOS :: MacOS X
Classifier: Operating System :: POSIX
Requires-Python: >=3
Requires-Dist: biobb-common (>=0.1.2)
Requires-Dist: biobb-io (>=0.1.4)
Requires-Dist: biobb-model (>=0.1.5)
Requires-Dist: biobb-md (>=0.1.5)
Requires-Dist: biobb-adapters (>=0.1.4)
